<?xml version="1.0" encoding="UTF-8"?>
<platform>
	<processor>
		<model>small</model>
		<number>1</number>
		<mode>
			<name>default</name>
			<cycle_length>1</cycle_length>
			<memorySize>10000</memorySize>
			<powerCons>50</powerCons>
			<areaCost>50</areaCost>
			<monetaryCost>100</monetaryCost>
		</mode>
		<mode>
			<name>economy</name>
			<cycle_length>1.2</cycle_length>
			<memorySize>10000</memorySize>
			<powerCons>30</powerCons>
			<areaCost>30</areaCost>
			<monetaryCost>70</monetaryCost>
		</mode>
	</processor>
	<processor>
		<model>large</model>
		<number>4</number>
		<mode>
			<name>default</name>
			<cycle_length>1</cycle_length>
			<memorySize>100000</memorySize>
			<powerCons>500</powerCons>
			<areaCost>500</areaCost>
			<monetaryCost>1000</monetaryCost>
		</mode>
	</processor>
</platform>
